multipart_reader/__init__.py
multipart_reader/compat.py
multipart_reader/errors.py
multipart_reader/hdrs.py
multipart_reader/helpers.py
multipart_reader/multidict.py
multipart_reader/multipart.py
multipart_reader/protocol.py
multipart_reader-0.2.dist-info/DESCRIPTION.rst
multipart_reader-0.2.dist-info/METADATA
multipart_reader-0.2.dist-info/RECORD
multipart_reader-0.2.dist-info/WHEEL
multipart_reader-0.2.dist-info/metadata.json
multipart_reader-0.2.dist-info/top_level.txt
