Metadata-Version: 2.0
Name: multipart-reader
Version: 0.2
Summary: Multipart/* reader extracted from awsome `aiohttp` project, cf.: http://aiohttp.readthedocs.org/en/stable/multipart.html.
Home-page: https://github.com/novafloss/multipart-reader
Author: Florent Pigout
Author-email: florent.pigout@people-doc.com
License: MIT
Keywords: multipart
Platform: UNKNOWN
Classifier: Development Status :: 4 - Beta
Classifier: Environment :: Console
Classifier: Intended Audience :: Developers
Classifier: License :: OSI Approved :: Apache Software License
Classifier: Programming Language :: Python
Requires-Dist: future
Requires-Dist: setuptools (>=17.1)
Provides-Extra: release
Requires-Dist: wheel; extra == 'release'
Requires-Dist: zest.releaser; extra == 'release'
Provides-Extra: test
Requires-Dist: flake8; extra == 'test'
Requires-Dist: unittest2; extra == 'test'
